README.rst
setup.py
mail_templated/__init__.py
max_django_mail_templated.egg-info/PKG-INFO
max_django_mail_templated.egg-info/SOURCES.txt
max_django_mail_templated.egg-info/dependency_links.txt
max_django_mail_templated.egg-info/top_level.txt