Metadata-Version: 1.1
Name: max-django-mail-templated
Version: 1.3
Summary: Send emails with Django template system
Home-page: https://github.com/maximilianhurl/django-mail-templated
Author: Artem Rizhov, Max hurl
Author-email: artem.rizhov@gmail.com
License: MIT
Platform: any
Classifier: Development Status :: 4 - Beta
Classifier: Intended Audience :: Developers
Classifier: License :: OSI Approved :: MIT License
Classifier: Operating System :: OS Independent
Classifier: Programming Language :: Python
Classifier: Topic :: Software Development :: Libraries :: Python Modules
Classifier: Framework :: Django
